rbino/__init__.py
rbino/rbino.py
rbino-1.0.2.dist-info/METADATA
rbino-1.0.2.dist-info/WHEEL
rbino-1.0.2.dist-info/top_level.txt
rbino-1.0.2.dist-info/RECORD
